{
  "events": [
    {
      "kind": "run_started",
      "payload": {
        "max_connected": 50,
        "model_routing": {
          "agents": {},
          "orchestrator": null
        },
        "repository": "/home/labestiadevigia/corvus-cronos-bridge"
      },
      "sequence": 0,
      "timestamp": "2026-07-19T18:28:03.491397+00:00"
    },
    {
      "kind": "phase_started",
      "payload": {
        "peak_rss_bytes": 98775040,
        "phase": "discovery"
      },
      "sequence": 1,
      "timestamp": "2026-07-19T18:28:03.492796+00:00"
    },
    {
      "kind": "phase_completed",
      "payload": {
        "elapsed_seconds": "0.079123",
        "peak_rss_bytes": 98775040,
        "phase": "discovery"
      },
      "sequence": 2,
      "timestamp": "2026-07-19T18:28:03.571928+00:00"
    },
    {
      "kind": "phase_started",
      "payload": {
        "peak_rss_bytes": 98775040,
        "phase": "triage"
      },
      "sequence": 3,
      "timestamp": "2026-07-19T18:28:03.573227+00:00"
    },
    {
      "kind": "repository_discovered",
      "payload": {
        "modules": 71,
        "stacks": [
          "Python",
          "JavaScript"
        ]
      },
      "sequence": 4,
      "timestamp": "2026-07-19T18:28:03.824875+00:00"
    },
    {
      "kind": "modules_classified",
      "payload": {
        "deletion_judgments": {
          "benchmark/benchmark.py": "deleting would remove unreachable code",
          "corvus/corvus/__init__.py": "deleting would remove unreachable code",
          "corvus/corvus/memory/__init__.py": "deleting would remove unreachable code",
          "corvus/corvus/verdict/__init__.py": "deleting would remove unreachable code",
          "corvus/mcp_server.py": "deleting would remove unreachable code",
          "cronos/demo_seed.py": "deleting would remove unreachable code",
          "cronos/mcp_server.py": "deleting would remove unreachable code",
          "cronos/recall.py": "deleting would remove unreachable code",
          "demo/dashboard_data.js": "deleting would remove unreachable code",
          "demo/export_dashboard_data.py": "deleting would remove unreachable code",
          "demo/export_static_demo.py": "deleting would remove unreachable code",
          "demo/render_cronos_report.py": "deleting would remove unreachable code",
          "web/demo-data.js": "deleting would remove unreachable code"
        },
        "summary": {
          "CONNECTED_ALIVE": 53,
          "DEAD_WEIGHT": 2,
          "DUPLICATE": 5,
          "FOSSIL_HIGH_RISK": 11
        }
      },
      "sequence": 5,
      "timestamp": "2026-07-19T18:28:03.826208+00:00"
    },
    {
      "kind": "phase_completed",
      "payload": {
        "elapsed_seconds": "0.254438",
        "peak_rss_bytes": 98775040,
        "phase": "triage"
      },
      "sequence": 6,
      "timestamp": "2026-07-19T18:28:03.827671+00:00"
    },
    {
      "kind": "sharding_required",
      "payload": {
        "connected_modules": 53,
        "max_connected": 50,
        "shard_count": 2
      },
      "sequence": 7,
      "timestamp": "2026-07-19T18:28:03.829153+00:00"
    },
    {
      "kind": "phase_started",
      "payload": {
        "peak_rss_bytes": 98775040,
        "phase": "shard_0001"
      },
      "sequence": 8,
      "timestamp": "2026-07-19T18:28:03.840687+00:00"
    },
    {
      "kind": "phase_completed",
      "payload": {
        "elapsed_seconds": "7.779313",
        "peak_rss_bytes": 103911424,
        "phase": "shard_0001"
      },
      "sequence": 9,
      "timestamp": "2026-07-19T18:28:11.620011+00:00"
    },
    {
      "kind": "phase_started",
      "payload": {
        "peak_rss_bytes": 103911424,
        "phase": "shard_0002"
      },
      "sequence": 10,
      "timestamp": "2026-07-19T18:28:11.620998+00:00"
    },
    {
      "kind": "phase_completed",
      "payload": {
        "elapsed_seconds": "2.201716",
        "peak_rss_bytes": 103911424,
        "phase": "shard_0002"
      },
      "sequence": 11,
      "timestamp": "2026-07-19T18:28:13.822722+00:00"
    },
    {
      "kind": "run_completed",
      "payload": {
        "findings": 73,
        "sharded": true
      },
      "sequence": 12,
      "timestamp": "2026-07-19T18:28:13.824497+00:00"
    }
  ],
  "run_id": "3e0cb778-3d78-4d0d-941d-99aacd3f1909",
  "started_at": "2026-07-19T18:28:03.474930+00:00",
  "trace_version": "1"
}
